LICENSE
README.rst
src/__init__.py
src/sus.py
sus-1.3.0.dist-info/entry_points.txt
sus-1.3.0.dist-info/LICENSE
sus-1.3.0.dist-info/WHEEL
sus-1.3.0.dist-info/METADATA
sus-1.3.0.dist-info/RECORD
