Metadata-Version: 2.1
Name: sus
Version: 1.3.0
Summary: Really simple static website URL shortener
Home-page: https://github.com/nkantar/sus
License: MIT
Keywords: static,url,shortener
Author: Nik Kantar
Author-email: nik@nkantar.com
Requires-Python: >=3.6,<4.0
Classifier: Development Status :: 5 - Production/Stable
Classifier: Environment :: Web Environment
Classifier: Intended Audience :: Developers
Classifier: License :: OSI Approved :: MIT License
Classifier: Programming Language :: Python :: 3
Classifier: Programming Language :: Python :: 3.6
Classifier: Programming Language :: Python :: 3.7
Classifier: Programming Language :: Python :: 3.8
Classifier: Programming Language :: Python :: 3.9
Classifier: Topic :: Internet :: WWW/HTTP
Classifier: Topic :: Software Development :: Code Generators
Classifier: Topic :: Software Development :: Libraries
Classifier: Topic :: Text Processing :: Markup
Classifier: Topic :: Utilities
Classifier: Typing :: Typed
Project-URL: Documentation, https://github.com/nkantar/sus
Project-URL: Repository, https://github.com/nkantar/sus
